datatlas/__init__.py
datatlas/datatlas_eda.py
datatlas/datatlas_missing_values.py
datatlas-1.0.4.dist-info/LICENSE
datatlas-1.0.4.dist-info/METADATA
datatlas-1.0.4.dist-info/WHEEL
datatlas-1.0.4.dist-info/top_level.txt
datatlas-1.0.4.dist-info/RECORD
